SC/__init__.py
SC/engine.py
SC_Engine-1.1.0.dist-info/METADATA
SC_Engine-1.1.0.dist-info/WHEEL
SC_Engine-1.1.0.dist-info/top_level.txt
SC_Engine-1.1.0.dist-info/zip-safe
SC_Engine-1.1.0.dist-info/RECORD
