Metadata-Version: 2.1
Name: SC-Engine
Version: 1.1.0
Summary: A rotation module
Home-page: 
Author: SplatCraft
Author-email: splatcraft.5972@gmail.com
License: GNU General Public License v3 (GPLv3)
Classifier: Programming Language :: Python :: 3
Classifier: License :: OSI Approved :: GNU General Public License v3 (GPLv3)
Classifier: Operating System :: OS Independent
Requires-Python: >=3.1
